pytakeout/__init__.py
pytakeout/takeout.py
pytakeout-0.1.0.dist-info/DESCRIPTION.rst
pytakeout-0.1.0.dist-info/METADATA
pytakeout-0.1.0.dist-info/RECORD
pytakeout-0.1.0.dist-info/WHEEL
pytakeout-0.1.0.dist-info/metadata.json
pytakeout-0.1.0.dist-info/top_level.txt
tests/__init__.py
tests/test_module.py
