Metadata-Version: 2.0
Name: pytakeout
Version: 0.1.0
Summary: Simplifies Python code extraction
Home-page: https://github.com/idlesign/pytakeout
Author: Igor `idle sign` Starikov
Author-email: idlesign@yandex.ru
License: BSD 3-Clause License
Platform: UNKNOWN
Classifier: Development Status :: 4 - Beta
Classifier: Operating System :: OS Independent
Classifier: Programming Language :: Python
Classifier: Programming Language :: Python :: 2
Classifier: Programming Language :: Python :: 2.7
Classifier: Programming Language :: Python :: 3.4
Classifier: Programming Language :: Python :: 3.5
Classifier: Programming Language :: Python :: 3.6
Classifier: License :: OSI Approved :: BSD License
